binnakle/__init__.py
binnakle/binnakle.py
binnakle/utils.py
binnakle-1.2308.1.dist-info/LICENSE
binnakle-1.2308.1.dist-info/METADATA
binnakle-1.2308.1.dist-info/WHEEL
binnakle-1.2308.1.dist-info/top_level.txt
binnakle-1.2308.1.dist-info/RECORD
