Metadata-Version: 2.1
Name: binnakle
Version: 1.2308.1
Summary: Contextualized logging library for Python.
Home-page: https://github.com/councilbox/binnakle-python
Author: Rodrigo Martínez Castaño
Author-email: rodrigo.martinez@councilbox.com
License: GNU General Public License v3 (GPLv3)
Classifier: Development Status :: 4 - Beta
Classifier: Environment :: Console
Classifier: Intended Audience :: Developers
Classifier: License :: OSI Approved :: GNU General Public License v3 (GPLv3)
Classifier: Operating System :: POSIX :: Linux
Classifier: Programming Language :: Python :: 3.6
Classifier: Programming Language :: Python :: Implementation :: PyPy
Classifier: Topic :: Software Development :: Libraries :: Python Modules
Requires-Python: >=3.6
License-File: LICENSE
